README.md
setup.cfg
setup.py
mbq/__init__.py
mbq.ranch.egg-info/PKG-INFO
mbq.ranch.egg-info/SOURCES.txt
mbq.ranch.egg-info/dependency_links.txt
mbq.ranch.egg-info/not-zip-safe
mbq.ranch.egg-info/requires.txt
mbq.ranch.egg-info/top_level.txt
mbq/ranch/__init__.py
mbq/ranch/__version__.py
mbq/ranch/admin.py
mbq/ranch/apps.py
mbq/ranch/constants.py
mbq/ranch/controllers.py
mbq/ranch/exceptions.py
mbq/ranch/killswitch.py
mbq/ranch/models.py
mbq/ranch/py.typed
mbq/ranch/lib/__init__.py
mbq/ranch/lib/error_handling.py
mbq/ranch/migrations/0001_initial.py
mbq/ranch/migrations/0002_loggedtask_queue.py
mbq/ranch/migrations/0003_loggedtask_rollbar_occurrence.py
mbq/ranch/migrations/__init__.py
mbq/ranch/signal_handlers/__init__.py
mbq/ranch/signal_handlers/config_handlers.py
mbq/ranch/signal_handlers/correlation_handlers.py
mbq/ranch/signal_handlers/metrics_handlers.py
mbq/ranch/signal_handlers/persistence_handlers.py
mbq/ranch/signal_handlers/rollbar_handlers.py
mbq/ranch/stats/__init__.py
mbq/ranch/stats/rabbitmq.py
tests/__init__.py
tests/celery.py
tests/launch_darkly.py
tests/settings.py
tests/tasks.py
tests/urls.py
tests/wsgi.py
tests/tests/__init__.py
tests/tests/settings.py
tests/tests/test_controllers.py
tests/tests/test_killswitch.py